tests/__init__.py
udp_logger/__init__.py
udp_logger/apm/__init__.py
udp_logger/apm/udp_apm.py
udp_logger/logger/__init__.py
udp_logger/logger/base_handler.py
udp_logger/logger/udp_handler.py
udp_mongo_logger-1.0.2.dist-info/licenses/LICENSE
udp_mongo_logger-1.0.2.dist-info/METADATA
udp_mongo_logger-1.0.2.dist-info/WHEEL
udp_mongo_logger-1.0.2.dist-info/top_level.txt
udp_mongo_logger-1.0.2.dist-info/RECORD
