Metadata-Version: 2.4
Name: udp-mongo-logger
Version: 1.0.2
Summary: APM and logging library with UDP integration
Home-page: https://github.com/single-service/udp-logger.git
Author: Aleksey Rybkin, Dmitriy Sosedov
Author-email: singleservice2022@gmail.com
License: MIT
Classifier: Programming Language :: Python :: 3
Classifier: License :: OSI Approved :: MIT License
Classifier: Operating System :: OS Independent
Requires-Python: >=3.7
License-File: LICENSE
Requires-Dist: typing_extensions
Requires-Dist: psutil
Dynamic: author
Dynamic: author-email
Dynamic: classifier
Dynamic: description
Dynamic: description-content-type
Dynamic: home-page
Dynamic: license
Dynamic: license-file
Dynamic: requires-dist
Dynamic: requires-python
Dynamic: summary
